jelly/__init__.py
jelly/client.py
jelly/html.py
jelly/logger.py
jelly/session.py
jelly/transport.py
jelly/util.py
web_jelly-0.1.1.dist-info/LICENSE
web_jelly-0.1.1.dist-info/METADATA
web_jelly-0.1.1.dist-info/WHEEL
web_jelly-0.1.1.dist-info/top_level.txt
web_jelly-0.1.1.dist-info/RECORD
