Metadata-Version: 2.1
Name: web-jelly
Version: 0.1.1
Summary: web-jelly.com python client
Home-page: https://web-jelly.com
Author: Jellyfish
Author-email: hello@web-jelly.com
License: UNKNOWN
Project-URL: Bug Tracker, https://gitlab.com/hello590/jelly-python-client/-/issues
Project-URL: Source, https://gitlab.com/hello590/jelly-python-client
Platform: UNKNOWN
Classifier: Programming Language :: Python :: 3
Classifier: License :: OSI Approved :: MIT License
Classifier: Operating System :: OS Independent
Requires-Python: >=3.6
License-File: LICENSE
Requires-Dist: paho-mqtt
